<?xml version="1.0" encoding="UTF-8" standalone="yes"?>
<addressBook>
    <city size="big">
        <name>Kyiv</name>
        <street>
            <name>Khreshatyk</name>
            <number number="1"/>
            <number number="2"/>
            <number number="3"/>
        </street>
        <street>
            <name>Kyrylivska</name>
            <number number="1"/>
            <number number="2"/>
            <number number="3"/>
        </street>
    </city>
    <city size="small">
        <name>Brovary</name>
        <street>
            <name>Kyivska</name>
            <number number="1"/>
            <number number="2"/>
        </street>
    </city>
</addressBook>
